Metadata-Version: 1.1
Name: Mopidy-YDisk
Version: 0.2.0
Summary: Mopidy extension for Yandex.Disk
Home-page: https://github.com/vonZeppelin/mopidy-ydisk
Author: Leonid Bogdanov
Author-email: leonid_bogdanov@mail.ru
License: Apache License, Version 2.0
Platform: UNKNOWN
Classifier: Environment :: No Input/Output (Daemon)
Classifier: Intended Audience :: End Users/Desktop
Classifier: License :: OSI Approved :: Apache Software License
Classifier: Operating System :: OS Independent
Classifier: Programming Language :: Python :: 2
Classifier: Topic :: Multimedia :: Sound/Audio :: Players
